soc_roman_tools/__init__.py
soc_roman_tools/version.py
soc_roman_tools/pixel_area/__init__.py
soc_roman_tools/pixel_area/pixel_area_map.py
soc_roman_tools/resources/__init__.py
soc_roman_tools/resources/data/__init__.py
soc_roman_tools/resources/data/roman_siaf.xml
soc_roman_tools/siaf/__init__.py
soc_roman_tools/siaf/siaf.py
soc_roman_tools/utilities/__init__.py
soc_roman_tools/utilities/logging_functions.py
soc_roman_tools/utilities/matrix.py
soc_roman_tools/utilities/pandeia_notebook.py
soc_roman_tools-0.1.0.dist-info/LICENSE
soc_roman_tools-0.1.0.dist-info/METADATA
soc_roman_tools-0.1.0.dist-info/WHEEL
soc_roman_tools-0.1.0.dist-info/top_level.txt
soc_roman_tools-0.1.0.dist-info/RECORD
