Metadata-Version: 2.1
Name: soc-roman-tools
Version: 0.1.0
Summary: Tools and examples for the Roman WFI developed by the Roman Science Operations Center.
Home-page: https://github.com/spacetelescope/soc_roman_tools
Author: STScI
Author-email: help@stsci.edu
License: BSD-3-Clause
Project-URL: Source Code, https://github.com/spacetelescope/soc_roman_tools
Classifier: Intended Audience :: Science/Research
Classifier: Topic :: Scientific/Engineering :: Astronomy
Classifier: License :: OSI Approved :: BSD License
Classifier: Programming Language :: Python :: 3
Requires-Python: >=3.8
License-File: LICENSE
Requires-Dist: roman-datamodels
Requires-Dist: pysiaf
Requires-Dist: scipy
Requires-Dist: matplotlib
